warned_dataclasses/__init__.py
warned_dataclasses/_internals.py
warned_dataclasses/common.py
warned_dataclasses/main.py
warned_dataclasses-0.5.1.dist-info/LICENSE
warned_dataclasses-0.5.1.dist-info/METADATA
warned_dataclasses-0.5.1.dist-info/WHEEL
warned_dataclasses-0.5.1.dist-info/top_level.txt
warned_dataclasses-0.5.1.dist-info/RECORD
