Metadata-Version: 2.1
Name: warned-dataclasses
Version: 0.5.1
Author-email: Angus L'Herrou <contact@lru.dev>
Classifier: License :: OSI Approved :: Apache Software License
Classifier: Programming Language :: Python :: 3
Classifier: Programming Language :: Python :: 3.7
Classifier: Programming Language :: Python :: 3.8
Classifier: Programming Language :: Python :: 3.9
Classifier: Programming Language :: Python :: 3.10
Classifier: Programming Language :: Python :: 3.11
Requires-Python: >=3.7
License-File: LICENSE
Requires-Dist: typing-extensions ; python_version < "3.10"
